cable_tester.v
`default_nettype none
`timescale 1ns / 100ps
module main (
	input  wire       clk, // clock signal from the board
	input  wire       rst, // reset signal from the board
    output reg ena,         // enable signal to ADG732
    output reg wr,           // write signal to ADG732
    output reg cs,           // chip select output for ADG732
    output reg [4:0] set_ch  // set output channel
);

localparam STATE_COUNTING = 2'd0 ; // counting - wr to low, count clock for division
localparam STATE_PREP = 2'd1 ; //states prep - set cs and new channel values 
localparam STATE_UPDATE= 2'd2 ; //update - load new values by wr l-> H
localparam CLK_DIVIDER = 24'd10000000; // clock divider value, 10M by default

reg [23:0] clk_count; //24 bit counter for 10 million clock divider
reg div_clk;
reg [1:0] state; // register keeping the machine state

always @(posedge clk) begin
    if (rst) begin
        clk_count=0;
        ena <= 0;
        div_clk <=0;
        state <= STATE_COUNTING;
        set_ch <=0;

    end
    if (clk_count>= CLK_DIVIDER) begin
        state <= STATE_PREP;        
        div_clk <= ~div_clk;
        clk_count <= 0;
        set_ch <= set_ch+1;
        wr <= 0;
        cs <=1;
        ena <= 0;
    end else begin
        clk_count <=  clk_count+1;
        cs <=0;
    end
    
    if (state==STATE_PREP) begin
     wr <= 1;
     cs <=1;
     state<=STATE_COUNTING;

    end

    if (state==STATE_COUNTING) begin
    wr <= 0;
    
    end
    


    if (set_ch>=25) begin
     set_ch<= 0;
    end
    

end

endmodule

cable_tester_tb.v
// timescale time precision
`timescale 1ns/10ps

//define testbench as a generic module

module cable_tester_tb();

// internal signals

wire [4:0] set_ch;
wire ena;
wire cs;
wire wr;




// storage elements (set initial values to zero)

reg clk = 0;
reg rst = 0;

// set parameters

localparam DURATION=40000;

// generate substitute clock signal 1/((2*41.67)*1ns)=11.999040.08 MHz

always begin

    //delay for 41.67 time units (ns) 
    #41.667
    clk=~clk;

end

// instantiate unit under test

main uut(
    .clk(clk),
    .rst(rst), 
    .set_ch(set_ch)
);



initial begin
    #100
    rst=1'b1;
    #200
    rst=1'b0;
end

// run simulation

initial begin

    $dumpfile("cable_tester_tb.vcd");
    $dumpvars(0, cable_tester_tb);
    #(DURATION)
    $display("finished");
    $finish;
end




endmodule

cable_tester_tb.vcd
$date
	Fri Jun 20 14:12:52 2025
$end
$version
	Icarus Verilog
$end
$timescale
	1ps
$end
$scope module cable_tester_tb $end
$var wire 5 ! set_ch [4:0] $end
$var parameter 32 " DURATION $end
$var reg 1 # clk $end
$var reg 1 $ rst $end
$scope module uut $end
$var wire 1 # clk $end
$var wire 1 $ rst $end
$var parameter 24 % CLK_DIVIDER $end
$var parameter 2 & STATE_COUNTING $end
$var parameter 2 ' STATE_PREP $end
$var parameter 2 ( STATE_UPDATE $end
$var reg 24 ) clk_count [23:0] $end
$var reg 1 * cs $end
$var reg 1 + div_clk $end
$var reg 1 , ena $end
$var reg 5 - set_ch [4:0] $end
$var reg 2 . state [1:0] $end
$var reg 1 / wr $end
$upscope $end
$upscope $end
$enddefinitions $end
$comment Show the parameter values. $end
$dumpall
b10 (
b1 '
b0 &
b1010 %
b1001110001000000 "
$end
#0
$dumpvars
x/
bx .
bx -
x,
x+
x*
bx )
0$
0#
bx !
$end
#41670
0*
1#
#83340
0#
#100000
1$
#125010
b0 !
b0 -
b0 .
0+
0,
b1 )
1#
#166680
0#
#208350
0/
b1 )
1#
#250020
0#
#291690
b1 )
1#
#300000
0$
#333360
0#
#375030
b10 )
1#
#416700
0#
#458370
b11 )
1#
#500040
0#
#541710
b100 )
1#
#583380
0#
#625050
b101 )
1#
#666720
0#
#708390
b110 )
1#
#750060
0#
#791730
b111 )
1#
#833400
0#
#875070
b1000 )
1#
#916740
0#
#958410
b1001 )
1#
#1000080
0#
#1041750
b1010 )
1#
#1083420
0#
#1125090
1*
b1 !
b1 -
b0 )
1+
b1 .
1#
#1166760
0#
#1208430
b0 .
1/
1*
b1 )
1#
#1250100
0#
#1291770
0/
0*
b10 )
1#
#1333440
0#
#1375110
b11 )
1#
#1416780
0#
#1458450
b100 )
1#
#1500120
0#
#1541790
b101 )
1#
#1583460
0#
#1625130
b110 )
1#
#1666800
0#
#1708470
b111 )
1#
#1750140
0#
#1791810
b1000 )
1#
#1833480
0#
#1875150
b1001 )
1#
#1916820
0#
#1958490
b1010 )
1#
#2000160
0#
#2041830
1*
b10 !
b10 -
b0 )
0+
b1 .
1#
#2083500
0#
#2125170
b0 .
1/
1*
b1 )
1#
#2166840
0#
#2208510
0/
0*
b10 )
1#
#2250180
0#
#2291850
b11 )
1#
#2333520
0#
#2375190
b100 )
1#
#2416860
0#
#2458530
b101 )
1#
#2500200
0#
#2541870
b110 )
1#
#2583540
0#
#2625210
b111 )
1#
#2666880
0#
#2708550
b1000 )
1#
#2750220
0#
#2791890
b1001 )
1#
#2833560
0#
#2875230
b1010 )
1#
#2916900
0#
#2958570
1*
b11 !
b11 -
b0 )
1+
b1 .
1#
#3000240
0#
#3041910
b0 .
1/
1*
b1 )
1#
#3083580
0#
#3125250
0/
0*
b10 )
1#
#3166920
0#
#3208590
b11 )
1#
#3250260
0#
#3291930
b100 )
1#
#3333600
0#
#3375270
b101 )
1#
#3416940
0#
#3458610
b110 )
1#
#3500280
0#
#3541950
b111 )
1#
#3583620
0#
#3625290
b1000 )
1#
#3666960
0#
#3708630
b1001 )
1#
#3750300
0#
#3791970
b1010 )
1#
#3833640
0#
#3875310
1*
b100 !
b100 -
b0 )
0+
b1 .
1#
#3916980
0#
#3958650
b0 .
1/
1*
b1 )
1#
#4000320
0#
#4041990
0/
0*
b10 )
1#
#4083660
0#
#4125330
b11 )
1#
#4167000
0#
#4208670
b100 )
1#
#4250340
0#
#4292010
b101 )
1#
#4333680
0#
#4375350
b110 )
1#
#4417020
0#
#4458690
b111 )
1#
#4500360
0#
#4542030
b1000 )
1#
#4583700
0#
#4625370
b1001 )
1#
#4667040
0#
#4708710
b1010 )
1#
#4750380
0#
#4792050
1*
b101 !
b101 -
b0 )
1+
b1 .
1#
#4833720
0#
#4875390
b0 .
1/
1*
b1 )
1#
#4917060
0#
#4958730
0/
0*
b10 )
1#
#5000400
0#
#5042070
b11 )
1#
#5083740
0#
#5125410
b100 )
1#
#5167080
0#
#5208750
b101 )
1#
#5250420
0#
#5292090
b110 )
1#
#5333760
0#
#5375430
b111 )
1#
#5417100
0#
#5458770
b1000 )
1#
#5500440
0#
#5542110
b1001 )
1#
#5583780
0#
#5625450
b1010 )
1#
#5667120
0#
#5708790
1*
b110 !
b110 -
b0 )
0+
b1 .
1#
#5750460
0#
#5792130
b0 .
1/
1*
b1 )
1#
#5833800
0#
#5875470
0/
0*
b10 )
1#
#5917140
0#
#5958810
b11 )
1#
#6000480
0#
#6042150
b100 )
1#
#6083820
0#
#6125490
b101 )
1#
#6167160
0#
#6208830
b110 )
1#
#6250500
0#
#6292170
b111 )
1#
#6333840
0#
#6375510
b1000 )
1#
#6417180
0#
#6458850
b1001 )
1#
#6500520
0#
#6542190
b1010 )
1#
#6583860
0#
#6625530
1*
b111 !
b111 -
b0 )
1+
b1 .
1#
#6667200
0#
#6708870
b0 .
1/
1*
b1 )
1#
#6750540
0#
#6792210
0/
0*
b10 )
1#
#6833880
0#
#6875550
b11 )
1#
#6917220
0#
#6958890
b100 )
1#
#7000560
0#
#7042230
b101 )
1#
#7083900
0#
#7125570
b110 )
1#
#7167240
0#
#7208910
b111 )
1#
#7250580
0#
#7292250
b1000 )
1#
#7333920
0#
#7375590
b1001 )
1#
#7417260
0#
#7458930
b1010 )
1#
#7500600
0#
#7542270
1*
b1000 !
b1000 -
b0 )
0+
b1 .
1#
#7583940
0#
#7625610
b0 .
1/
1*
b1 )
1#
#7667280
0#
#7708950
0/
0*
b10 )
1#
#7750620
0#
#7792290
b11 )
1#
#7833960
0#
#7875630
b100 )
1#
#7917300
0#
#7958970
b101 )
1#
#8000640
0#
#8042310
b110 )
1#
#8083980
0#
#8125650
b111 )
1#
#8167320
0#
#8208990
b1000 )
1#
#8250660
0#
#8292330
b1001 )
1#
#8334000
0#
#8375670
b1010 )
1#
#8417340
0#
#8459010
1*
b1001 !
b1001 -
b0 )
1+
b1 .
1#
#8500680
0#
#8542350
b0 .
1/
1*
b1 )
1#
#8584020
0#
#8625690
0/
0*
b10 )
1#
#8667360
0#
#8709030
b11 )
1#
#8750700
0#
#8792370
b100 )
1#
#8834040
0#
#8875710
b101 )
1#
#8917380
0#
#8959050
b110 )
1#
#9000720
0#
#9042390
b111 )
1#
#9084060
0#
#9125730
b1000 )
1#
#9167400
0#
#9209070
b1001 )
1#
#9250740
0#
#9292410
b1010 )
1#
#9334080
0#
#9375750
1*
b1010 !
b1010 -
b0 )
0+
b1 .
1#
#9417420
0#
#9459090
b0 .
1/
1*
b1 )
1#
#9500760
0#
#9542430
0/
0*
b10 )
1#
#9584100
0#
#9625770
b11 )
1#
#9667440
0#
#9709110
b100 )
1#
#9750780
0#
#9792450
b101 )
1#
#9834120
0#
#9875790
b110 )
1#
#9917460
0#
#9959130
b111 )
1#
#10000800
0#
#10042470
b1000 )
1#
#10084140
0#
#10125810
b1001 )
1#
#10167480
0#
#10209150
b1010 )
1#
#10250820
0#
#10292490
1*
b1011 !
b1011 -
b0 )
1+
b1 .
1#
#10334160
0#
#10375830
b0 .
1/
1*
b1 )
1#
#10417500
0#
#10459170
0/
0*
b10 )
1#
#10500840
0#
#10542510
b11 )
1#
#10584180
0#
#10625850
b100 )
1#
#10667520
0#
#10709190
b101 )
1#
#10750860
0#
#10792530
b110 )
1#
#10834200
0#
#10875870
b111 )
1#
#10917540
0#
#10959210
b1000 )
1#
#11000880
0#
#11042550
b1001 )
1#
#11084220
0#
#11125890
b1010 )
1#
#11167560
0#
#11209230
1*
b1100 !
b1100 -
b0 )
0+
b1 .
1#
#11250900
0#
#11292570
b0 .
1/
1*
b1 )
1#
#11334240
0#
#11375910
0/
0*
b10 )
1#
#11417580
0#
#11459250
b11 )
1#
#11500920
0#
#11542590
b100 )
1#
#11584260
0#
#11625930
b101 )
1#
#11667600
0#
#11709270
b110 )
1#
#11750940
0#
#11792610
b111 )
1#
#11834280
0#
#11875950
b1000 )
1#
#11917620
0#
#11959290
b1001 )
1#
#12000960
0#
#12042630
b1010 )
1#
#12084300
0#
#12125970
1*
b1101 !
b1101 -
b0 )
1+
b1 .
1#
#12167640
0#
#12209310
b0 .
1/
1*
b1 )
1#
#12250980
0#
#12292650
0/
0*
b10 )
1#
#12334320
0#
#12375990
b11 )
1#
#12417660
0#
#12459330
b100 )
1#
#12501000
0#
#12542670
b101 )
1#
#12584340
0#
#12626010
b110 )
1#
#12667680
0#
#12709350
b111 )
1#
#12751020
0#
#12792690
b1000 )
1#
#12834360
0#
#12876030
b1001 )
1#
#12917700
0#
#12959370
b1010 )
1#
#13001040
0#
#13042710
1*
b1110 !
b1110 -
b0 )
0+
b1 .
1#
#13084380
0#
#13126050
b0 .
1/
1*
b1 )
1#
#13167720
0#
#13209390
0/
0*
b10 )
1#
#13251060
0#
#13292730
b11 )
1#
#13334400
0#
#13376070
b100 )
1#
#13417740
0#
#13459410
b101 )
1#
#13501080
0#
#13542750
b110 )
1#
#13584420
0#
#13626090
b111 )
1#
#13667760
0#
#13709430
b1000 )
1#
#13751100
0#
#13792770
b1001 )
1#
#13834440
0#
#13876110
b1010 )
1#
#13917780
0#
#13959450
1*
b1111 !
b1111 -
b0 )
1+
b1 .
1#
#14001120
0#
#14042790
b0 .
1/
1*
b1 )
1#
#14084460
0#
#14126130
0/
0*
b10 )
1#
#14167800
0#
#14209470
b11 )
1#
#14251140
0#
#14292810
b100 )
1#
#14334480
0#
#14376150
b101 )
1#
#14417820
0#
#14459490
b110 )
1#
#14501160
0#
#14542830
b111 )
1#
#14584500
0#
#14626170
b1000 )
1#
#14667840
0#
#14709510
b1001 )
1#
#14751180
0#
#14792850
b1010 )
1#
#14834520
0#
#14876190
1*
b10000 !
b10000 -
b0 )
0+
b1 .
1#
#14917860
0#
#14959530
b0 .
1/
1*
b1 )
1#
#15001200
0#
#15042870
0/
0*
b10 )
1#
#15084540
0#
#15126210
b11 )
1#
#15167880
0#
#15209550
b100 )
1#
#15251220
0#
#15292890
b101 )
1#
#15334560
0#
#15376230
b110 )
1#
#15417900
0#
#15459570
b111 )
1#
#15501240
0#
#15542910
b1000 )
1#
#15584580
0#
#15626250
b1001 )
1#
#15667920
0#
#15709590
b1010 )
1#
#15751260
0#
#15792930
1*
b10001 !
b10001 -
b0 )
1+
b1 .
1#
#15834600
0#
#15876270
b0 .
1/
1*
b1 )
1#
#15917940
0#
#15959610
0/
0*
b10 )
1#
#16001280
0#
#16042950
b11 )
1#
#16084620
0#
#16126290
b100 )
1#
#16167960
0#
#16209630
b101 )
1#
#16251300
0#
#16292970
b110 )
1#
#16334640
0#
#16376310
b111 )
1#
#16417980
0#
#16459650
b1000 )
1#
#16501320
0#
#16542990
b1001 )
1#
#16584660
0#
#16626330
b1010 )
1#
#16668000
0#
#16709670
1*
b10010 !
b10010 -
b0 )
0+
b1 .
1#
#16751340
0#
#16793010
b0 .
1/
1*
b1 )
1#
#16834680
0#
#16876350
0/
0*
b10 )
1#
#16918020
0#
#16959690
b11 )
1#
#17001360
0#
#17043030
b100 )
1#
#17084700
0#
#17126370
b101 )
1#
#17168040
0#
#17209710
b110 )
1#
#17251380
0#
#17293050
b111 )
1#
#17334720
0#
#17376390
b1000 )
1#
#17418060
0#
#17459730
b1001 )
1#
#17501400
0#
#17543070
b1010 )
1#
#17584740
0#
#17626410
1*
b10011 !
b10011 -
b0 )
1+
b1 .
1#
#17668080
0#
#17709750
b0 .
1/
1*
b1 )
1#
#17751420
0#
#17793090
0/
0*
b10 )
1#
#17834760
0#
#17876430
b11 )
1#
#17918100
0#
#17959770
b100 )
1#
#18001440
0#
#18043110
b101 )
1#
#18084780
0#
#18126450
b110 )
1#
#18168120
0#
#18209790
b111 )
1#
#18251460
0#
#18293130
b1000 )
1#
#18334800
0#
#18376470
b1001 )
1#
#18418140
0#
#18459810
b1010 )
1#
#18501480
0#
#18543150
1*
b10100 !
b10100 -
b0 )
0+
b1 .
1#
#18584820
0#
#18626490
b0 .
1/
1*
b1 )
1#
#18668160
0#
#18709830
0/
0*
b10 )
1#
#18751500
0#
#18793170
b11 )
1#
#18834840
0#
#18876510
b100 )
1#
#18918180
0#
#18959850
b101 )
1#
#19001520
0#
#19043190
b110 )
1#
#19084860
0#
#19126530
b111 )
1#
#19168200
0#
#19209870
b1000 )
1#
#19251540
0#
#19293210
b1001 )
1#
#19334880
0#
#19376550
b1010 )
1#
#19418220
0#
#19459890
1*
b10101 !
b10101 -
b0 )
1+
b1 .
1#
#19501560
0#
#19543230
b0 .
1/
1*
b1 )
1#
#19584900
0#
#19626570
0/
0*
b10 )
1#
#19668240
0#
#19709910
b11 )
1#
#19751580
0#
#19793250
b100 )
1#
#19834920
0#
#19876590
b101 )
1#
#19918260
0#
#19959930
b110 )
1#
#20001600
0#
#20043270
b111 )
1#
#20084940
0#
#20126610
b1000 )
1#
#20168280
0#
#20209950
b1001 )
1#
#20251620
0#
#20293290
b1010 )
1#
#20334960
0#
#20376630
1*
b10110 !
b10110 -
b0 )
0+
b1 .
1#
#20418300
0#
#20459970
b0 .
1/
1*
b1 )
1#
#20501640
0#
#20543310
0/
0*
b10 )
1#
#20584980
0#
#20626650
b11 )
1#
#20668320
0#
#20709990
b100 )
1#
#20751660
0#
#20793330
b101 )
1#
#20835000
0#
#20876670
b110 )
1#
#20918340
0#
#20960010
b111 )
1#
#21001680
0#
#21043350
b1000 )
1#
#21085020
0#
#21126690
b1001 )
1#
#21168360
0#
#21210030
b1010 )
1#
#21251700
0#
#21293370
1*
b10111 !
b10111 -
b0 )
1+
b1 .
1#
#21335040
0#
#21376710
b0 .
1/
1*
b1 )
1#
#21418380
0#
#21460050
0/
0*
b10 )
1#
#21501720
0#
#21543390
b11 )
1#
#21585060
0#
#21626730
b100 )
1#
#21668400
0#
#21710070
b101 )
1#
#21751740
0#
#21793410
b110 )
1#
#21835080
0#
#21876750
b111 )
1#
#21918420
0#
#21960090
b1000 )
1#
#22001760
0#
#22043430
b1001 )
1#
#22085100
0#
#22126770
b1010 )
1#
#22168440
0#
#22210110
1*
b11000 !
b11000 -
b0 )
0+
b1 .
1#
#22251780
0#
#22293450
b0 .
1/
1*
b1 )
1#
#22335120
0#
#22376790
0/
0*
b10 )
1#
#22418460
0#
#22460130
b11 )
1#
#22501800
0#
#22543470
b100 )
1#
#22585140
0#
#22626810
b101 )
1#
#22668480
0#
#22710150
b110 )
1#
#22751820
0#
#22793490
b111 )
1#
#22835160
0#
#22876830
b1000 )
1#
#22918500
0#
#22960170
b1001 )
1#
#23001840
0#
#23043510
b1010 )
1#
#23085180
0#
#23126850
1*
b11001 !
b11001 -
b0 )
1+
b1 .
1#
#23168520
0#
#23210190
b0 !
b0 -
b0 .
1/
1*
b1 )
1#
#23251860
0#
#23293530
0/
0*
b10 )
1#
#23335200
0#
#23376870
b11 )
1#
#23418540
0#
#23460210
b100 )
1#
#23501880
0#
#23543550
b101 )
1#
#23585220
0#
#23626890
b110 )
1#
#23668560
0#
#23710230
b111 )
1#
#23751900
0#
#23793570
b1000 )
1#
#23835240
0#
#23876910
b1001 )
1#
#23918580
0#
#23960250
b1010 )
1#
#24001920
0#
#24043590
1*
b1 !
b1 -
b0 )
0+
b1 .
1#
#24085260
0#
#24126930
b0 .
1/
1*
b1 )
1#
#24168600
0#
#24210270
0/
0*
b10 )
1#
#24251940
0#
#24293610
b11 )
1#
#24335280
0#
#24376950
b100 )
1#
#24418620
0#
#24460290
b101 )
1#
#24501960
0#
#24543630
b110 )
1#
#24585300
0#
#24626970
b111 )
1#
#24668640
0#
#24710310
b1000 )
1#
#24751980
0#
#24793650
b1001 )
1#
#24835320
0#
#24876990
b1010 )
1#
#24918660
0#
#24960330
1*
b10 !
b10 -
b0 )
1+
b1 .
1#
#25002000
0#
#25043670
b0 .
1/
1*
b1 )
1#
#25085340
0#
#25127010
0/
0*
b10 )
1#
#25168680
0#
#25210350
b11 )
1#
#25252020
0#
#25293690
b100 )
1#
#25335360
0#
#25377030
b101 )
1#
#25418700
0#
#25460370
b110 )
1#
#25502040
0#
#25543710
b111 )
1#
#25585380
0#
#25627050
b1000 )
1#
#25668720
0#
#25710390
b1001 )
1#
#25752060
0#
#25793730
b1010 )
1#
#25835400
0#
#25877070
1*
b11 !
b11 -
b0 )
0+
b1 .
1#
#25918740
0#
#25960410
b0 .
1/
1*
b1 )
1#
#26002080
0#
#26043750
0/
0*
b10 )
1#
#26085420
0#
#26127090
b11 )
1#
#26168760
0#
#26210430
b100 )
1#
#26252100
0#
#26293770
b101 )
1#
#26335440
0#
#26377110
b110 )
1#
#26418780
0#
#26460450
b111 )
1#
#26502120
0#
#26543790
b1000 )
1#
#26585460
0#
#26627130
b1001 )
1#
#26668800
0#
#26710470
b1010 )
1#
#26752140
0#
#26793810
1*
b100 !
b100 -
b0 )
1+
b1 .
1#
#26835480
0#
#26877150
b0 .
1/
1*
b1 )
1#
#26918820
0#
#26960490
0/
0*
b10 )
1#
#27002160
0#
#27043830
b11 )
1#
#27085500
0#
#27127170
b100 )
1#
#27168840
0#
#27210510
b101 )
1#
#27252180
0#
#27293850
b110 )
1#
#27335520
0#
#27377190
b111 )
1#
#27418860
0#
#27460530
b1000 )
1#
#27502200
0#
#27543870
b1001 )
1#
#27585540
0#
#27627210
b1010 )
1#
#27668880
0#
#27710550
1*
b101 !
b101 -
b0 )
0+
b1 .
1#
#27752220
0#
#27793890
b0 .
1/
1*
b1 )
1#
#27835560
0#
#27877230
0/
0*
b10 )
1#
#27918900
0#
#27960570
b11 )
1#
#28002240
0#
#28043910
b100 )
1#
#28085580
0#
#28127250
b101 )
1#
#28168920
0#
#28210590
b110 )
1#
#28252260
0#
#28293930
b111 )
1#
#28335600
0#
#28377270
b1000 )
1#
#28418940
0#
#28460610
b1001 )
1#
#28502280
0#
#28543950
b1010 )
1#
#28585620
0#
#28627290
1*
b110 !
b110 -
b0 )
1+
b1 .
1#
#28668960
0#
#28710630
b0 .
1/
1*
b1 )
1#
#28752300
0#
#28793970
0/
0*
b10 )
1#
#28835640
0#
#28877310
b11 )
1#
#28918980
0#
#28960650
b100 )
1#
#29002320
0#
#29043990
b101 )
1#
#29085660
0#
#29127330
b110 )
1#
#29169000
0#
#29210670
b111 )
1#
#29252340
0#
#29294010
b1000 )
1#
#29335680
0#
#29377350
b1001 )
1#
#29419020
0#
#29460690
b1010 )
1#
#29502360
0#
#29544030
1*
b111 !
b111 -
b0 )
0+
b1 .
1#
#29585700
0#
#29627370
b0 .
1/
1*
b1 )
1#
#29669040
0#
#29710710
0/
0*
b10 )
1#
#29752380
0#
#29794050
b11 )
1#
#29835720
0#
#29877390
b100 )
1#
#29919060
0#
#29960730
b101 )
1#
#30002400
0#
#30044070
b110 )
1#
#30085740
0#
#30127410
b111 )
1#
#30169080
0#
#30210750
b1000 )
1#
#30252420
0#
#30294090
b1001 )
1#
#30335760
0#
#30377430
b1010 )
1#
#30419100
0#
#30460770
1*
b1000 !
b1000 -
b0 )
1+
b1 .
1#
#30502440
0#
#30544110
b0 .
1/
1*
b1 )
1#
#30585780
0#
#30627450
0/
0*
b10 )
1#
#30669120
0#
#30710790
b11 )
1#
#30752460
0#
#30794130
b100 )
1#
#30835800
0#
#30877470
b101 )
1#
#30919140
0#
#30960810
b110 )
1#
#31002480
0#
#31044150
b111 )
1#
#31085820
0#
#31127490
b1000 )
1#
#31169160
0#
#31210830
b1001 )
1#
#31252500
0#
#31294170
b1010 )
1#
#31335840
0#
#31377510
1*
b1001 !
b1001 -
b0 )
0+
b1 .
1#
#31419180
0#
#31460850
b0 .
1/
1*
b1 )
1#
#31502520
0#
#31544190
0/
0*
b10 )
1#
#31585860
0#
#31627530
b11 )
1#
#31669200
0#
#31710870
b100 )
1#
#31752540
0#
#31794210
b101 )
1#
#31835880
0#
#31877550
b110 )
1#
#31919220
0#
#31960890
b111 )
1#
#32002560
0#
#32044230
b1000 )
1#
#32085900
0#
#32127570
b1001 )
1#
#32169240
0#
#32210910
b1010 )
1#
#32252580
0#
#32294250
1*
b1010 !
b1010 -
b0 )
1+
b1 .
1#
#32335920
0#
#32377590
b0 .
1/
1*
b1 )
1#
#32419260
0#
#32460930
0/
0*
b10 )
1#
#32502600
0#
#32544270
b11 )
1#
#32585940
0#
#32627610
b100 )
1#
#32669280
0#
#32710950
b101 )
1#
#32752620
0#
#32794290
b110 )
1#
#32835960
0#
#32877630
b111 )
1#
#32919300
0#
#32960970
b1000 )
1#
#33002640
0#
#33044310
b1001 )
1#
#33085980
0#
#33127650
b1010 )
1#
#33169320
0#
#33210990
1*
b1011 !
b1011 -
b0 )
0+
b1 .
1#
#33252660
0#
#33294330
b0 .
1/
1*
b1 )
1#
#33336000
0#
#33377670
0/
0*
b10 )
1#
#33419340
0#
#33461010
b11 )
1#
#33502680
0#
#33544350
b100 )
1#
#33586020
0#
#33627690
b101 )
1#
#33669360
0#
#33711030
b110 )
1#
#33752700
0#
#33794370
b111 )
1#
#33836040
0#
#33877710
b1000 )
1#
#33919380
0#
#33961050
b1001 )
1#
#34002720
0#
#34044390
b1010 )
1#
#34086060
0#
#34127730
1*
b1100 !
b1100 -
b0 )
1+
b1 .
1#
#34169400
0#
#34211070
b0 .
1/
1*
b1 )
1#
#34252740
0#
#34294410
0/
0*
b10 )
1#
#34336080
0#
#34377750
b11 )
1#
#34419420
0#
#34461090
b100 )
1#
#34502760
0#
#34544430
b101 )
1#
#34586100
0#
#34627770
b110 )
1#
#34669440
0#
#34711110
b111 )
1#
#34752780
0#
#34794450
b1000 )
1#
#34836120
0#
#34877790
b1001 )
1#
#34919460
0#
#34961130
b1010 )
1#
#35002800
0#
#35044470
1*
b1101 !
b1101 -
b0 )
0+
b1 .
1#
#35086140
0#
#35127810
b0 .
1/
1*
b1 )
1#
#35169480
0#
#35211150
0/
0*
b10 )
1#
#35252820
0#
#35294490
b11 )
1#
#35336160
0#
#35377830
b100 )
1#
#35419500
0#
#35461170
b101 )
1#
#35502840
0#
#35544510
b110 )
1#
#35586180
0#
#35627850
b111 )
1#
#35669520
0#
#35711190
b1000 )
1#
#35752860
0#
#35794530
b1001 )
1#
#35836200
0#
#35877870
b1010 )
1#
#35919540
0#
#35961210
1*
b1110 !
b1110 -
b0 )
1+
b1 .
1#
#36002880
0#
#36044550
b0 .
1/
1*
b1 )
1#
#36086220
0#
#36127890
0/
0*
b10 )
1#
#36169560
0#
#36211230
b11 )
1#
#36252900
0#
#36294570
b100 )
1#
#36336240
0#
#36377910
b101 )
1#
#36419580
0#
#36461250
b110 )
1#
#36502920
0#
#36544590
b111 )
1#
#36586260
0#
#36627930
b1000 )
1#
#36669600
0#
#36711270
b1001 )
1#
#36752940
0#
#36794610
b1010 )
1#
#36836280
0#
#36877950
1*
b1111 !
b1111 -
b0 )
0+
b1 .
1#
#36919620
0#
#36961290
b0 .
1/
1*
b1 )
1#
#37002960
0#
#37044630
0/
0*
b10 )
1#
#37086300
0#
#37127970
b11 )
1#
#37169640
0#
#37211310
b100 )
1#
#37252980
0#
#37294650
b101 )
1#
#37336320
0#
#37377990
b110 )
1#
#37419660
0#
#37461330
b111 )
1#
#37503000
0#
#37544670
b1000 )
1#
#37586340
0#
#37628010
b1001 )
1#
#37669680
0#
#37711350
b1010 )
1#
#37753020
0#
#37794690
1*
b10000 !
b10000 -
b0 )
1+
b1 .
1#
#37836360
0#
#37878030
b0 .
1/
1*
b1 )
1#
#37919700
0#
#37961370
0/
0*
b10 )
1#
#38003040
0#
#38044710
b11 )
1#
#38086380
0#
#38128050
b100 )
1#
#38169720
0#
#38211390
b101 )
1#
#38253060
0#
#38294730
b110 )
1#
#38336400
0#
#38378070
b111 )
1#
#38419740
0#
#38461410
b1000 )
1#
#38503080
0#
#38544750
b1001 )
1#
#38586420
0#
#38628090
b1010 )
1#
#38669760
0#
#38711430
1*
b10001 !
b10001 -
b0 )
0+
b1 .
1#
#38753100
0#
#38794770
b0 .
1/
1*
b1 )
1#
#38836440
0#
#38878110
0/
0*
b10 )
1#
#38919780
0#
#38961450
b11 )
1#
#39003120
0#
#39044790
b100 )
1#
#39086460
0#
#39128130
b101 )
1#
#39169800
0#
#39211470
b110 )
1#
#39253140
0#
#39294810
b111 )
1#
#39336480
0#
#39378150
b1000 )
1#
#39419820
0#
#39461490
b1001 )
1#
#39503160
0#
#39544830
b1010 )
1#
#39586500
0#
#39628170
1*
b10010 !
b10010 -
b0 )
1+
b1 .
1#
#39669840
0#
#39711510
b0 .
1/
1*
b1 )
1#
#39753180
0#
#39794850
0/
0*
b10 )
1#
#39836520
0#
#39878190
b11 )
1#
#39919860
0#
#39961530
b100 )
1#
